niche_image/__init__.py
niche_image/services/configs/model_config.yaml
nicheimage-0.0.2.dist-info/METADATA
nicheimage-0.0.2.dist-info/WHEEL
nicheimage-0.0.2.dist-info/top_level.txt
nicheimage-0.0.2.dist-info/RECORD
