Metadata-Version: 2.1
Name: nicheimage
Version: 0.0.2
Summary: Subnet 23 - Bittensor
Home-page: https://github.com/NicheTensor/NicheImage
Author: NicheImage dev
Author-email: NicheImage dev <tranthanhluan.nd@gmail.com>
License: MIT License
Project-URL: Homepage, https://github.com/NicheTensor/NicheImage
Project-URL: Issues, https://github.com/NicheTensor/NicheImage/issues
Classifier: Programming Language :: Python :: 3
Classifier: License :: OSI Approved :: MIT License
Classifier: Operating System :: OS Independent
Requires-Python: >=3.8
